fastlite_migrations/__init__.py
fastlite_migrations/_modidx.py
fastlite_migrations/core.py
fastlite_migrations-0.0.2.dist-info/LICENSE
fastlite_migrations-0.0.2.dist-info/METADATA
fastlite_migrations-0.0.2.dist-info/WHEEL
fastlite_migrations-0.0.2.dist-info/entry_points.txt
fastlite_migrations-0.0.2.dist-info/top_level.txt
fastlite_migrations-0.0.2.dist-info/RECORD
